{
    "id": "56078e6ab6472632750237d9",
    "balance": "$1,688.84",
    "picture": "http://placehold.it/32x32",
    "age": 37,
    "eyeColor": "brown",
    "name": "Janie Spence",
    "gender": "female",
    "company": "CENTREXIN",
    "email": "janiespence@centrexin.com",
    "phone": "+1 (810) 593-3088",
    "address": "887 Doscher Street, Rodman, Ohio, 2281",
    "about": "Cupidatat reprehenderit velit culpa mollit culpa incididunt. Sunt dolor aliqua magna cillum amet ipsum et minim. Quis exercitation eu reprehenderit sit mollit aliqua aliquip amet.\r\n",
    "registered": "2014-01-12T06:03:00 -06:-30",
    "latitude": 36.678678,
    "longitude": 145.260941,
    "greeting": "Hello, Janie Spence! You have 1 unread messages.",
    "favoriteFruit": "strawberry"
}